setup.py
debrfstats/RFSStats.py
debrfstats/__init__.py
debrfstats/get_done_date.py
debrfstats.egg-info/PKG-INFO
debrfstats.egg-info/SOURCES.txt
debrfstats.egg-info/dependency_links.txt
debrfstats.egg-info/not-zip-safe
debrfstats.egg-info/requires.txt
debrfstats.egg-info/top_level.txt