Metadata-Version: 1.1
Name: debrfstats
Version: 0.0.1
Summary: debrfstats is a library to generate Debian RFS statistics
Home-page: https://github.com/tdi/debrfstats
Author: Dariusz Dwornikowski
Author-email: dariusz.dwornikowski@cs.put.poznan.pl
License: GPL-3
Platform: UNKNOWN
Classifier: Environment :: Console
Classifier: Development Status :: 4 - Beta
Classifier: Programming Language :: Python
Classifier: Programming Language :: Python :: 2.7
Classifier: Operating System :: POSIX
Requires: SOAPpy (>=0.12.0)
Requires: dateutil (>=1.4)
Requires: requests (>=2.3.0)
